py_eddy_tracker_sample/__init__.py
py_eddy_tracker_sample/_version.py
py_eddy_tracker_sample/eddies_med_adt_allsat_dt2018/Anticyclonic.zarr/.zattrs
py_eddy_tracker_sample/eddies_med_adt_allsat_dt2018/Anticyclonic.zarr/.zgroup
py_eddy_tracker_sample/eddies_med_adt_allsat_dt2018/Anticyclonic.zarr/amplitude/.zarray
py_eddy_tracker_sample/eddies_med_adt_allsat_dt2018/Anticyclonic.zarr/amplitude/.zattrs
py_eddy_tracker_sample/eddies_med_adt_allsat_dt2018/Anticyclonic.zarr/amplitude/0
py_eddy_tracker_sample/eddies_med_adt_allsat_dt2018/Anticyclonic.zarr/latitude/.zarray
py_eddy_tracker_sample/eddies_med_adt_allsat_dt2018/Anticyclonic.zarr/latitude/.zattrs
py_eddy_tracker_sample/eddies_med_adt_allsat_dt2018/Anticyclonic.zarr/latitude/0
py_eddy_tracker_sample/eddies_med_adt_allsat_dt2018/Anticyclonic.zarr/longitude/.zarray
py_eddy_tracker_sample/eddies_med_adt_allsat_dt2018/Anticyclonic.zarr/longitude/.zattrs
py_eddy_tracker_sample/eddies_med_adt_allsat_dt2018/Anticyclonic.zarr/longitude/0
py_eddy_tracker_sample/eddies_med_adt_allsat_dt2018/Anticyclonic.zarr/observation_flag/.zarray
py_eddy_tracker_sample/eddies_med_adt_allsat_dt2018/Anticyclonic.zarr/observation_flag/.zattrs
py_eddy_tracker_sample/eddies_med_adt_allsat_dt2018/Anticyclonic.zarr/observation_flag/0
py_eddy_tracker_sample/eddies_med_adt_allsat_dt2018/Anticyclonic.zarr/observation_number/.zarray
py_eddy_tracker_sample/eddies_med_adt_allsat_dt2018/Anticyclonic.zarr/observation_number/.zattrs
py_eddy_tracker_sample/eddies_med_adt_allsat_dt2018/Anticyclonic.zarr/observation_number/0
py_eddy_tracker_sample/eddies_med_adt_allsat_dt2018/Anticyclonic.zarr/speed_average/.zarray
py_eddy_tracker_sample/eddies_med_adt_allsat_dt2018/Anticyclonic.zarr/speed_average/.zattrs
py_eddy_tracker_sample/eddies_med_adt_allsat_dt2018/Anticyclonic.zarr/speed_average/0
py_eddy_tracker_sample/eddies_med_adt_allsat_dt2018/Anticyclonic.zarr/speed_contour_latitude/.zarray
pyEddyTrackerSample-0.1.0.dist-info/COPYING
pyEddyTrackerSample-0.1.0.dist-info/METADATA
pyEddyTrackerSample-0.1.0.dist-info/WHEEL
pyEddyTrackerSample-0.1.0.dist-info/top_level.txt
pyEddyTrackerSample-0.1.0.dist-info/RECORD
