Metadata-Version: 2.1
Name: pyEddyTrackerSample
Version: 0.1.0
Summary: Py-Eddy-Tracker samples
Home-page: UNKNOWN
Author: Antoine Delepoulle
Author-email: delepoulle.a@gmail.com
License: UNKNOWN
Keywords: eddy samples
Platform: UNKNOWN
